clitable/__init__.py
clitable/presets.py
clitable-0.2.1.dist-info/METADATA
clitable-0.2.1.dist-info/WHEEL
clitable-0.2.1.dist-info/licenses/LICENSE.txt
clitable-0.2.1.dist-info/RECORD
