Metadata-Version: 2.1
Name: clitable
Version: 0.2.1
Summary: Create table representations from various data structures, using either simple ASCII characters or unicode box-drawing characters.
Project-URL: Source, https://github.com/proggy/clitable
Project-URL: Homepage, https://github.com/proggy/clitable
Project-URL: Bug Tracker, https://github.com/proggy/clitable/issues
Author-email: Daniel Jung <proggy-contact@mailbox.org>
Maintainer-email: Daniel Jung <proggy-contact@mailbox.org>
License-File: LICENSE.txt
Classifier: License :: OSI Approved :: GNU General Public License v2 (GPLv2)
Classifier: Operating System :: OS Independent
Classifier: Programming Language :: Python :: 3
Requires-Python: >=3.7
